miniswhid/__init__.py
miniswhid/cli.py
miniswhid/miniswhid.py
miniswhid/py.typed
miniswhid-0.1.0.dist-info/METADATA
miniswhid-0.1.0.dist-info/WHEEL
miniswhid-0.1.0.dist-info/entry_points.txt
miniswhid-0.1.0.dist-info/licenses/LICENSE
miniswhid-0.1.0.dist-info/RECORD
