Metadata-Version: 2.4
Name: miniswhid
Version: 0.1.0
Summary: No-frills SWHID computation for files and directories
Project-URL: Homepage, https://github.com/diegojorquera/miniswhid
Project-URL: Repository, https://github.com/diegojorquera/miniswhid
Project-URL: Issues, https://github.com/diegojorquera/miniswhid/issues
Author: Diego Jorquera
License-Expression: MIT
License-File: LICENSE
Keywords: hash,identifier,software-heritage,swhid
Classifier: Development Status :: 4 - Beta
Classifier: Intended Audience :: Developers
Classifier: Programming Language :: Python :: 3
Classifier: Programming Language :: Python :: 3.10
Classifier: Programming Language :: Python :: 3.11
Classifier: Programming Language :: Python :: 3.12
Classifier: Programming Language :: Python :: 3.13
Classifier: Topic :: Software Development :: Libraries :: Python Modules
Classifier: Topic :: System :: Archiving
Classifier: Topic :: Utilities
Requires-Python: >=3.10
